pyensys/__init__.py
pyensys/cases.py
pyensys/cli.py
pyensys/fixtures.py
pyensys/run.py
pyensys/engines/__init__.py
pyensys/engines/debugger.py
pyensys/engines/main.py
pyensys/engines/pyeneD.py
pyensys/engines/pyeneE.py
pyensys/engines/pyeneH.py
pyensys/engines/pyeneI.py
pyensys/engines/pyeneN.py
pyensys/engines/pyeneO.py
pyensys/engines/pyeneP.py
pyensys/engines/pyeneR.py
pyensys/engines/pyene_Analizer.py
pyensys/engines/pyene_Models.py
pyensys/engines/pyene_Parameters.py
pyensys/engines/pyene_Stochastic.py
pyensys/engines/pyene_Tree.py
pyensys/engines/cython/__init__.py
pyensys/engines/cython/_glpk.cp38-win_amd64.pyd
pyensys/engines/cython/cpp_energy_wrapper.cp38-win_amd64.pyd
pyensys/json/ResolutionTreeMonth01.json
pyensys/json/ResolutionTreeYear01.json
pyensys/json/ResolutionTreeYear03.json
pyensys/json/TestCase.json
pyensys/json/TimeSeries.json
pyensys/json/TreeMonth01_01RD.json
pyensys/json/UKElectricityProfiles.json
pyensys/json/case14.json
pyensys/json/case14_con.json
pyensys/json/case4.json
pyensys/json/case4Test.json
pyensys/json/caseH4.json
pyensys-0.0.3.dist-info/LICENSE.txt
pyensys-0.0.3.dist-info/METADATA
pyensys-0.0.3.dist-info/WHEEL
pyensys-0.0.3.dist-info/entry_points.txt
pyensys-0.0.3.dist-info/top_level.txt
pyensys-0.0.3.dist-info/RECORD
